thriving_api/__init__.py
thriving_api/base_client.py
thriving_api/client.py
thriving_api/exceptions.py
thriving_api/rate_limiter.py
thriving_api/models/__init__.py
thriving_api/models/ai.py
thriving_api/models/base.py
thriving_api/models/company.py
thriving_api/models/market.py
thriving_api/models/options.py
thriving_api/models/symbol.py
thriving_api/models/technical.py
thriving_api/modules/__init__.py
thriving_api/modules/ai.py
thriving_api/modules/company.py
thriving_api/modules/market.py
thriving_api/modules/options.py
thriving_api/modules/symbol.py
thriving_api/modules/technical.py
thriving_api-1.0.6.dist-info/licenses/LICENSE
thriving_api-1.0.6.dist-info/METADATA
thriving_api-1.0.6.dist-info/WHEEL
thriving_api-1.0.6.dist-info/top_level.txt
thriving_api-1.0.6.dist-info/RECORD
