Metadata-Version: 2.4
Name: thriving-api
Version: 1.0.6
Summary: Official Python SDK for the Thriving API - AI-powered financial analysis and trading intelligence
Author-email: Thriving <support@tradethriving.com>
Maintainer-email: Thriving <support@tradethriving.com>
License: MIT
Project-URL: Homepage, https://tradethriving.com
Project-URL: Documentation, https://tradethriving.com/api-documentation
Project-URL: Repository, https://github.com/thriving/thriving-api-python
Project-URL: Bug Tracker, https://github.com/thriving/thriving-api-python/issues
Project-URL: API Documentation, https://tradethriving.com/api-documentation
Keywords: trading,finance,api,stocks,ai,machine-learning,technical-analysis,market-data,financial-data,investment
Classifier: Development Status :: 5 - Production/Stable
Classifier: Intended Audience :: Developers
Classifier: Intended Audience :: Financial and Insurance Industry
Classifier: License :: OSI Approved :: MIT License
Classifier: Operating System :: OS Independent
Classifier: Programming Language :: Python :: 3
Classifier: Programming Language :: Python :: 3.10
Classifier: Programming Language :: Python :: 3.11
Classifier: Programming Language :: Python :: 3.12
Classifier: Topic :: Office/Business :: Financial :: Investment
Classifier: Topic :: Software Development :: Libraries :: Python Modules
Classifier: Topic :: Scientific/Engineering :: Artificial Intelligence
Requires-Python: >=3.10
License-File: LICENSE
Requires-Dist: httpx>=0.25.0
Requires-Dist: pydantic>=2.0.0
Requires-Dist: typing-extensions>=4.0.0
Requires-Dist: python-dateutil>=2.8.0
Provides-Extra: dev
Requires-Dist: pytest>=7.0.0; extra == "dev"
Requires-Dist: pytest-asyncio>=0.21.0; extra == "dev"
Requires-Dist: pytest-cov>=4.0.0; extra == "dev"
Requires-Dist: black>=23.0.0; extra == "dev"
Requires-Dist: isort>=5.12.0; extra == "dev"
Requires-Dist: flake8>=6.0.0; extra == "dev"
Requires-Dist: mypy>=1.0.0; extra == "dev"
Requires-Dist: pre-commit>=3.0.0; extra == "dev"
Provides-Extra: docs
Requires-Dist: sphinx>=6.0.0; extra == "docs"
Requires-Dist: sphinx-rtd-theme>=1.2.0; extra == "docs"
Requires-Dist: sphinx-autodoc-typehints>=1.20.0; extra == "docs"
Dynamic: license-file
